rooster_client/__init__.py
rooster_client/api_pb2.py
rooster_client/api_pb2_grpc.py
rooster_client/grpc_error_metadata.py
rooster_client/rooster.py
rooster_client/test_rooster.py
rooster_client-0.0.1.data/scripts/rooster
rooster_client-0.0.1.dist-info/METADATA
rooster_client-0.0.1.dist-info/WHEEL
rooster_client-0.0.1.dist-info/top_level.txt
rooster_client-0.0.1.dist-info/RECORD
