Metadata-Version: 2.1
Name: rooster-client
Version: 0.0.1
Summary: Rooster Python client
Home-page: https://github.com/productsupcom/rooster-python-sdk
Author: Yorick Terweijden
Author-email: yt@productsup.com
Requires-Dist: argcomplete (==2.0.0)
Requires-Dist: astor (==0.8.1)
Requires-Dist: attrs (==22.1.0)
Requires-Dist: autoflake (==2.0.0)
Requires-Dist: black (==22.10.0)
Requires-Dist: cfgv (==3.3.1)
Requires-Dist: charset-normalizer (==2.1.1)
Requires-Dist: click (==8.1.3)
Requires-Dist: colorama (==0.4.6)
Requires-Dist: com2ann (==0.3.0)
Requires-Dist: commitizen (==2.37.1)
Requires-Dist: decli (==0.5.2)
Requires-Dist: distlib (==0.3.6)
Requires-Dist: filelock (==3.8.0)
Requires-Dist: ghp-import (==2.1.0)
Requires-Dist: googleapis-common-protos (==1.57.0)
Requires-Dist: grpcio (==1.51.1)
Requires-Dist: identify (==2.5.9)
Requires-Dist: interrogate (==1.5.0)
Requires-Dist: isort (==5.10.1)
Requires-Dist: Jinja2 (==3.1.2)
Requires-Dist: libcst (==0.4.9)
Requires-Dist: Mako (==1.2.4)
Requires-Dist: Markdown (==3.3.7)
Requires-Dist: MarkupSafe (==2.1.1)
Requires-Dist: mergedeep (==1.3.4)
Requires-Dist: mkdocs (==1.4.2)
Requires-Dist: mkdocs-autorefs (==0.4.1)
Requires-Dist: mkdocstrings (==0.19.0)
Requires-Dist: mkgendocs (==0.9.2)
Requires-Dist: mypy-extensions (==0.4.3)
Requires-Dist: nodeenv (==1.7.0)
Requires-Dist: packaging (==21.3)
Requires-Dist: pathspec (==0.10.2)
Requires-Dist: platformdirs (==2.5.4)
Requires-Dist: pre-commit (==2.20.0)
Requires-Dist: prompt-toolkit (==3.0.33)
Requires-Dist: protobuf (==4.21.10)
Requires-Dist: py (==1.11.0)
Requires-Dist: pyflakes (==3.0.1)
Requires-Dist: pymdown-extensions (==9.9)
Requires-Dist: pyparsing (==3.0.9)
Requires-Dist: python-dateutil (==2.8.2)
Requires-Dist: pyupgrade (==3.3.0)
Requires-Dist: PyYAML (==6.0)
Requires-Dist: pyyaml-env-tag (==0.1)
Requires-Dist: questionary (==1.10.0)
Requires-Dist: shed (==0.10.7)
Requires-Dist: six (==1.16.0)
Requires-Dist: tabulate (==0.9.0)
Requires-Dist: termcolor (==2.1.1)
Requires-Dist: tokenize-rt (==5.0.0)
Requires-Dist: toml (==0.10.2)
Requires-Dist: tomli (==2.0.1)
Requires-Dist: tomlkit (==0.11.6)
Requires-Dist: typing-inspect (==0.8.0)
Requires-Dist: typing-extensions (==4.4.0)
Requires-Dist: virtualenv (==20.17.0)
Requires-Dist: watchdog (==2.1.9)
Requires-Dist: wcwidth (==0.2.5)
